<?xml version="1.0" encoding="UTF-8"?>
<CountRequest CountRequestKey="" CountRequestNo="" DocumentType="" Node="">
    <LocationInventoryAudits >
        <LocationInventoryAudit AuditOperation=" " BolNo=" " CaseId=" "
            CountRequestKey=" " CountryOfOrigin=" " EnterpriseCode=" " 
			FifoNo=" " InventoryItemKey=" " InventoryStatus=" " 
			InventoryTagKey=" " LocationId=" " LocnInventoryAuditKey=" "  
			Node=" " OrderNo=" " OuterMostCaseId=" " OuterMostPalletId=" "
            PalletId=" " PrimeLineNo=" " Quantity=" " ReasonCode=" "
            ReasonText=" " ReceiptHeaderKey=" " Reference1=" "
            Reference2=" " Reference3=" " Reference4=" " Reference5=" "
            ReleaseNo=" " Segment=" " SegmentType=" " SequenceNo=""
            SerialNo=" " ShipByDate=" " ShipmentNo=" " TaskType=" ">
            <TagDetail InventoryItemKey=" " InventoryTagKey=" " 
                LotAttribute1=" " LotAttribute2=" " LotAttribute3=" "
                LotExpirationDate=" " LotKeyReference=" " LotNumber=" "
                ManufacturingDate=" " RevisionNo=" " 
                TotalDemand=" " TotalOnhandSupply=" " TotalOtherSupply=" "/>
            <InventoryItem  InventoryItemKey=" " InventoryOrganizationCode=" " 
				ItemID=" " ProductClass=" " UnitOfMeasure=" ">
                <Item ItemID="" ItemKey="" OrganizationCode="" UnitOfMeasure="">
                    <PrimaryInformation Description="" ShortDescription=""/>
                </Item>
            </InventoryItem>
            <Receipt ReceiptNo=" " ReceivingNode=" " ShipmentKey=" "/>
        </LocationInventoryAudit>
    </LocationInventoryAudits>
</CountRequest>