<?xml version="1.0" encoding="UTF-8"?>
<PickStrategy Description="" Node="" PickStrategyKey="">
	<PlaUomConditionList>
		<PlaUomCondition Description="" Node="" PickStrategyKey="" PlaItemConditionKey="" PlaUomConditionKey="" RetrievalStrategyKey="" SeqNo="">
			<PlaConditionAttrList>
			  <PlaConditionAttr AttrName="" Node="" PlaConditionAttrKey="" PlaUomConditionKey="" Value="" /> 
			</PlaConditionAttrList>
			<PlaZoneSetList>
				<PlaZoneSet Description="" Node="" PickAlgorithmCode="" PickFenceFactor="" PlaUomConditionKey="" PlaZoneSetKey="" Priority="" UseDedicatedLocations="" UseDynamicLocations="" ReplenishToMaxQty="" ReplenishBelowMinQty="">
					<PlaZoneAttrList>
					  <PlaZoneAttr AttrName="" Node="" PlaZoneAttrKey="" PlaZoneSetKey="" Value="" /> 
					 </PlaZoneAttrList>
					<PlaActivityTaskTypes>
					  <PlaActivityTaskType Activity="" Node="" PlaActivityTaskTypeKey="" PlaZoneSetKey="" TaskType="" /> 
					</PlaActivityTaskTypes>
					<PlaUpgradeUomList>
						<PlaUpgradeUom Node="" PlaZoneSetKey="" UOM=""/>
					</PlaUpgradeUomList>
				</PlaZoneSet>
			</PlaZoneSetList>
		</PlaUomCondition>
	</PlaUomConditionList>
	<PlaActivityDeterList>
	  <PlaActivityDeter ActivityCode="" ConsiderDemand="" Description="" EnterpriseCode="" ExcludeCaseFromDemand="" ExcludePalletFromDemand="" ItemClassification1="" ItemClassification2="" ItemClassification3="" MinNoOfPackages="" MinNoOfPackagesUOM="" MinNoOfSingleUnitCarton="" MinNoOfSingleUnitShipment="" Node="" PickStrategyKey="" PlaActivityDeterKey="" ShipMode="" SingleLineShipment="" SingleUnitShipment="" UOM="" /> 
	</PlaActivityDeterList>
	<PlaItemConditionList>
		<PlaItemCondition Node="" PickStrategyKey="" RetrievalStrategyKey="" Description="" ItemClassification1="" ItemClassification2="" ItemClassification3="" EnterpriseCode="" SeqNo=""/>
	</PlaItemConditionList>
</PickStrategy>